microllm/__init__.py
microllm/callbacks/__init__.py
microllm/evals/__init__.py
microllm/llms/__init__.py
microllm/llms/llm.py
microllm/llms/message_history.py
microllm/tools/__init__.py
microllm-0.0.1.dist-info/licenses/LICENSE
microllm-0.0.1.dist-info/METADATA
microllm-0.0.1.dist-info/WHEEL
microllm-0.0.1.dist-info/top_level.txt
microllm-0.0.1.dist-info/RECORD
