Metadata-Version: 2.4
Name: microllm
Version: 0.0.1
Summary: MicrolLM - Simple, Explicit and Transparent LLM Apps
Author: Stoyan Stoyanov
Project-URL: Homepage, https://github.com/stoyan-stoyanov/microllm
Project-URL: github, https://github.com/stoyan-stoyanov/microllm
Classifier: Programming Language :: Python :: 3
Classifier: License :: OSI Approved :: MIT License
Classifier: Operating System :: OS Independent
Requires-Python: >=3.9
License-File: LICENSE
Requires-Dist: openai==1.93.0
Requires-Dist: anthropic==0.57.1
Requires-Dist: tiktoken==0.9.0
Requires-Dist: black==25.1.0
Requires-Dist: pinecone-client==5.0.1
Requires-Dist: mkdocs-material==9.6.15
Requires-Dist: mkdocstrings==0.29.1
Requires-Dist: mkdocstrings-python==1.16.12
Requires-Dist: google-generativeai==0.8.5
Requires-Dist: pytest==8.4.1
Requires-Dist: pytest-asyncio==1.0.0
Dynamic: license-file
